pacman/__init__.py
pacman/main.py
pacman/pacman.py
pacman_play-0.0.1.dist-info/LICENSE
pacman_play-0.0.1.dist-info/METADATA
pacman_play-0.0.1.dist-info/WHEEL
pacman_play-0.0.1.dist-info/entry_points.txt
pacman_play-0.0.1.dist-info/top_level.txt
pacman_play-0.0.1.dist-info/RECORD
