Metadata-Version: 2.1
Name: pacman-play
Version: 0.0.1
Summary: Pacman game in terminal.
Home-page: https://github.com/phuang1024/pacman
Author: Patrick Huang
Author-email: phuang1024@gmail.com
License: UNKNOWN
Platform: UNKNOWN
Classifier: Programming Language :: Python :: 3
Classifier: License :: OSI Approved :: GNU General Public License v3 or later (GPLv3+)
Classifier: Operating System :: OS Independent
License-File: LICENSE
